modulefgoiriz/__init__.py
modulefgoiriz-0.1.0.dist-info/WHEEL
modulefgoiriz-0.1.0.dist-info/METADATA
modulefgoiriz-0.1.0.dist-info/RECORD
