Metadata-Version: 2.1
Name: modulefgoiriz
Version: 0.1.0
Summary: My super cool Python module.
Author-email: modulefgoiriz <modulefgoiriz@example.com>
